[{
  "_id": {
    "$oid": "5eb4ef26d894280774fd2228"
  },
  "totalPrice": 2,
  "products": [{
    "quantity": 1,
    "_id": {
      "$oid": "5eb4ef26d894280774fd2229"
    },
    "product": {
      "$oid": "5eb3af807567bf6778ad2428"
    }
  }],
  "owner": {
    "$oid": "5eb2f9619759944ccc21b36c"
  },
  "__v": 0
}, {
  "_id": {
    "$oid": "5eb4efd2e337500bb4e03ac3"
  },
  "totalPrice": 2,
  "products": [{
    "quantity": 1,
    "_id": {
      "$oid": "5eb4efd2e337500bb4e03ac4"
    },
    "product": {
      "$oid": "5eb3af807567bf6778ad2428"
    }
  }],
  "owner": {
    "$oid": "5eb2f9619759944ccc21b36c"
  },
  "__v": 0
}, {
  "_id": {
    "$oid": "5eb4f04ca3840b1db409bfd4"
  },
  "totalPrice": 2,
  "products": [{
    "quantity": 1,
    "_id": {
      "$oid": "5eb4f04ca3840b1db409bfd5"
    },
    "product": {
      "$oid": "5eb3af807567bf6778ad2428"
    }
  }],
  "owner": {
    "$oid": "5eb2f9619759944ccc21b36c"
  },
  "__v": 0
}, {
  "_id": {
    "$oid": "5eb4f0a576f6ef1278f05efd"
  },
  "totalPrice": 2,
  "products": [{
    "quantity": 1,
    "_id": {
      "$oid": "5eb4f0a576f6ef1278f05efe"
    },
    "product": {
      "$oid": "5eb3af807567bf6778ad2428"
    }
  }],
  "owner": {
    "$oid": "5eb2f9619759944ccc21b36c"
  },
  "__v": 0
}, {
  "_id": {
    "$oid": "5eb4f27b9e693437189eb880"
  },
  "totalPrice": 2,
  "products": [{
    "quantity": 1,
    "_id": {
      "$oid": "5eb4f27b9e693437189eb881"
    },
    "product": {
      "$oid": "5eb3af807567bf6778ad2428"
    }
  }],
  "owner": {
    "$oid": "5eb2f9619759944ccc21b36c"
  },
  "__v": 0
}, {
  "_id": {
    "$oid": "5eb4f2bc9e693437189eb882"
  },
  "totalPrice": 2,
  "products": [{
    "quantity": 1,
    "_id": {
      "$oid": "5eb4f2bc9e693437189eb883"
    },
    "product": {
      "$oid": "5eb3af807567bf6778ad2428"
    }
  }],
  "owner": {
    "$oid": "5eb2f9619759944ccc21b36c"
  },
  "__v": 0
}, {
  "_id": {
    "$oid": "5eb4f40cabbb042f3867ff56"
  },
  "totalPrice": 2,
  "products": [{
    "quantity": 1,
    "_id": {
      "$oid": "5eb4f40cabbb042f3867ff57"
    },
    "product": {
      "$oid": "5eb3af807567bf6778ad2428"
    }
  }],
  "owner": {
    "$oid": "5eb2f9619759944ccc21b36c"
  },
  "__v": 0
}, {
  "_id": {
    "$oid": "5eb4f5142b8bda2188f7ff6a"
  },
  "totalPrice": 2,
  "products": [{
    "quantity": 1,
    "_id": {
      "$oid": "5eb4f5142b8bda2188f7ff6b"
    },
    "product": {
      "$oid": "5eb3af807567bf6778ad2428"
    }
  }],
  "owner": {
    "$oid": "5eb2f9619759944ccc21b36c"
  },
  "__v": 0
}, {
  "_id": {
    "$oid": "5eb4f59a31fe171f7caa9e4b"
  },
  "totalPrice": 2,
  "products": [{
    "quantity": 1,
    "_id": {
      "$oid": "5eb4f59a31fe171f7caa9e4c"
    },
    "product": {
      "$oid": "5eb3af807567bf6778ad2428"
    }
  }],
  "owner": {
    "$oid": "5eb2f9619759944ccc21b36c"
  },
  "__v": 0
}, {
  "_id": {
    "$oid": "5eb4f81ca8e5333618704c1d"
  },
  "totalPrice": 2,
  "products": [{
    "quantity": 1,
    "_id": {
      "$oid": "5eb4f81ca8e5333618704c1e"
    },
    "product": {
      "$oid": "5eb3af807567bf6778ad2428"
    }
  }],
  "owner": {
    "$oid": "5eb2f9619759944ccc21b36c"
  },
  "__v": 0
}, {
  "_id": {
    "$oid": "5eb4f838a8e5333618704c1f"
  },
  "totalPrice": 2,
  "products": [{
    "quantity": 1,
    "_id": {
      "$oid": "5eb4f838a8e5333618704c20"
    },
    "product": {
      "$oid": "5eb3af807567bf6778ad2428"
    }
  }],
  "owner": {
    "$oid": "5eb2f9619759944ccc21b36c"
  },
  "__v": 0
}, {
  "_id": {
    "$oid": "5eb4f8a2294e1739e02f6886"
  },
  "totalPrice": 2,
  "products": [{
    "quantity": 1,
    "_id": {
      "$oid": "5eb4f8a2294e1739e02f6887"
    },
    "product": {
      "$oid": "5eb3af807567bf6778ad2428"
    }
  }],
  "owner": {
    "$oid": "5eb2f9619759944ccc21b36c"
  },
  "__v": 0
}, {
  "_id": {
    "$oid": "5eb4f905369b7826b4de8e0a"
  },
  "totalPrice": 2,
  "products": [{
    "quantity": 1,
    "_id": {
      "$oid": "5eb4f905369b7826b4de8e0b"
    },
    "product": {
      "$oid": "5eb3af807567bf6778ad2428"
    }
  }],
  "owner": {
    "$oid": "5eb2f9619759944ccc21b36c"
  },
  "__v": 0
}, {
  "_id": {
    "$oid": "5eb4fa917b21ee56c483a9b0"
  },
  "totalPrice": 2,
  "products": [{
    "quantity": 1,
    "_id": {
      "$oid": "5eb4fa917b21ee56c483a9b1"
    },
    "product": {
      "$oid": "5eb3af807567bf6778ad2428"
    }
  }],
  "owner": {
    "$oid": "5eb2f9619759944ccc21b36c"
  },
  "__v": 0
}, {
  "_id": {
    "$oid": "5eb4faa77b21ee56c483a9b2"
  },
  "totalPrice": 4,
  "products": [{
    "quantity": 2,
    "_id": {
      "$oid": "5eb4faa77b21ee56c483a9b3"
    },
    "product": {
      "$oid": "5eb3af807567bf6778ad2428"
    }
  }],
  "owner": {
    "$oid": "5eb2f9619759944ccc21b36c"
  },
  "__v": 0
}, {
  "_id": {
    "$oid": "5eb4feee7b21ee56c483a9b8"
  },
  "totalPrice": 3000,
  "products": [{
    "quantity": 2,
    "_id": {
      "$oid": "5eb4feee7b21ee56c483a9b9"
    },
    "product": {
      "$oid": "5eb4fb257b21ee56c483a9b4"
    }
  }],
  "owner": {
    "$oid": "5eb2f9619759944ccc21b36c"
  },
  "__v": 0
}, {
  "_id": {
    "$oid": "5eb5759d31747d1d941a9ee5"
  },
  "totalPrice": 100,
  "products": [{
    "quantity": 1,
    "_id": {
      "$oid": "5eb5759d31747d1d941a9ee6"
    },
    "product": {
      "$oid": "5eb4fb507b21ee56c483a9b5"
    }
  }],
  "owner": {
    "$oid": "5eb2f9619759944ccc21b36c"
  },
  "__v": 0
}, {
  "_id": {
    "$oid": "5eb5947b47acee117f9c78f8"
  },
  "totalPrice": 300,
  "products": [{
    "quantity": 3,
    "_id": {
      "$oid": "5eb5947b47acee117f9c78f9"
    },
    "product": {
      "$oid": "5eb5932916f89710796d962c"
    }
  }],
  "owner": {
    "$oid": "5eb235af597873d8d0f65ad9"
  },
  "__v": 0
}, {
  "_id": {
    "$oid": "5eb5949347acee117f9c78fa"
  },
  "totalPrice": 100,
  "products": [{
    "quantity": 1,
    "_id": {
      "$oid": "5eb5949347acee117f9c78fb"
    },
    "product": {
      "$oid": "5eb5932916f89710796d962c"
    }
  }],
  "owner": {
    "$oid": "5eb235af597873d8d0f65ad9"
  },
  "__v": 0
}, {
  "_id": {
    "$oid": "5eb5a8a923a85118dee48144"
  },
  "totalPrice": 1500,
  "products": [{
    "quantity": 1,
    "_id": {
      "$oid": "5eb5a8a923a85118dee48145"
    },
    "product": {
      "$oid": "5eb4fb257b21ee56c483a9b4"
    }
  }],
  "owner": {
    "$oid": "5eb235af597873d8d0f65ad9"
  },
  "__v": 0
}, {
  "_id": {
    "$oid": "5eb5da0c5c70912b990e69ef"
  },
  "totalPrice": 3890,
  "products": [{
      "quantity": 1,
      "_id": {
        "$oid": "5eb5da0c5c70912b990e69f0"
      },
      "product": {
        "$oid": "5eb4fba87b21ee56c483a9b7"
      }
    },
    {
      "quantity": 5,
      "_id": {
        "$oid": "5eb5da0c5c70912b990e69f1"
      },
      "product": {
        "$oid": "5eb4fb847b21ee56c483a9b6"
      }
    }
  ],
  "owner": {
    "$oid": "5eb5cbb1a100a129a71be67b"
  },
  "__v": 0
}]